NOTICE
pgmerge/__init__.py
pgmerge/db_config.py
pgmerge/db_export.py
pgmerge/db_graph.py
pgmerge/db_import.py
pgmerge/db_inspect.py
pgmerge/pg_pass.py
pgmerge/pgmerge.py
pgmerge/tables_config_schema.yml
pgmerge/utils.py
pgmerge-1.13.0.dist-info/LICENSE
pgmerge-1.13.0.dist-info/METADATA
pgmerge-1.13.0.dist-info/WHEEL
pgmerge-1.13.0.dist-info/entry_points.txt
pgmerge-1.13.0.dist-info/RECORD
