Metadata-Version: 2.1
Name: pgmerge
Version: 1.13.0
Summary: PostgreSQL data import/export utility
Home-page: https://github.com/samuller/pgmerge
Keywords: postgresql,csv,import,export
Author: Simon Muller
Author-email: samullers@gmail.com
Requires-Python: >=3.7,<4.0
Classifier: Development Status :: 5 - Production/Stable
Classifier: Environment :: Console
Classifier: Intended Audience :: Developers
Classifier: License :: OSI Approved :: Apache Software License
Classifier: Natural Language :: English
Classifier: Programming Language :: Python :: 3
Classifier: Programming Language :: Python :: 3.7
Classifier: Programming Language :: Python :: 3.8
Classifier: Programming Language :: Python :: 3.9
Classifier: Programming Language :: Python :: 3.10
Classifier: Programming Language :: Python :: 3.11
Classifier: Programming Language :: Python :: 3 :: Only
Classifier: Topic :: Database
Classifier: Topic :: Utilities
Requires-Dist: PyYAML (==6.0.1)
Requires-Dist: SQLAlchemy (==2.0.30)
Requires-Dist: fastjsonschema (==2.19.1)
Requires-Dist: networkx (==2.5)
Requires-Dist: platformdirs (==4.0.0)
Requires-Dist: psycopg2-binary
Requires-Dist: typer-slim (==0.12.3)
Project-URL: Repository, https://github.com/samuller/pgmerge
